sdd2rdf/__init__.py
sdd2rdf/sdd2rdf.py
sdd2rdf/sdd2setl.py
sdd2rdf/templates/sdd_setl_template.jinja
sdd2rdf-0.1.6.dist-info/LICENSE
sdd2rdf-0.1.6.dist-info/METADATA
sdd2rdf-0.1.6.dist-info/WHEEL
sdd2rdf-0.1.6.dist-info/entry_points.txt
sdd2rdf-0.1.6.dist-info/top_level.txt
sdd2rdf-0.1.6.dist-info/RECORD
