Metadata-Version: 2.1
Name: sdd2rdf
Version: 0.1.6
Summary: sdd2rdf generates RDF graphs from semantically annotated data.
Home-page: http://packages.python.org/sdd2rdf
Author: Jamie McCusker
Author-email: mccusj@cs.rpi.edu
License: Apache License 2.0
Keywords: rdf semantic etl
Platform: UNKNOWN
Classifier: Development Status :: 5 - Production/Stable
Classifier: Topic :: Utilities
Classifier: License :: OSI Approved :: Apache Software License
Requires-Dist: future
Requires-Dist: rdflib
Requires-Dist: rdflib-jsonld
Requires-Dist: setlr
Requires-Dist: bsddb3
Requires-Dist: jinja2
Requires-Dist: openpyxl
Requires-Dist: python-magic
Requires-Dist: python-slugify
Requires-Dist: pandas (>=0.23.0)
